Metadata-Version: 1.1
Name: famog
Version: 0.1
Summary: A package for Facts API
Home-page: https://elian-1.gitbook.io/facts-api/
Author: Elian Galdamez
Author-email: elian.galdamez510@gmail.com
License: MIT
Keywords: API
Platform: UNKNOWN
Classifier: Development Status :: 5 - Production/Stable
Classifier: Intended Audience :: Education
Classifier: Operating System :: Microsoft :: Windows :: Windows 10
Classifier: License :: OSI Approved :: MIT License
Classifier: Programming Language :: Python :: 3
